mobly/controllers/android_device_lib/services/__init__.py
mobly/controllers/android_device_lib/services/screen_recorder.py
mobly/controllers/android_device_lib/services/screen_recorder_test.py
mobly/controllers/android_device_lib/services/data/scrcpy-server-v3.3.jar
mobly/controllers/android_device_lib/services/data/scrcpy-server-v3.jar
mobly/controllers/android_device_lib/services/data/scrcpy-server.apk
mobly_android_screen_recorder-1.0.3.dist-info/licenses/LICENSE
mobly_android_screen_recorder-1.0.3.dist-info/licenses/NOTICE
mobly_android_screen_recorder-1.0.3.dist-info/METADATA
mobly_android_screen_recorder-1.0.3.dist-info/WHEEL
mobly_android_screen_recorder-1.0.3.dist-info/top_level.txt
mobly_android_screen_recorder-1.0.3.dist-info/RECORD
