Metadata-Version: 2.4
Name: mobly-android-screen-recorder
Version: 1.0.3
Summary: Mobly Android Screen Recorder service for using Python code to screencast the Android devices in Mobly tests.
Home-page: https://github.com/google/mobly-android-screen-recorder
Author: Google Inc.
Author-email: yayao@google.com
Maintainer-email: Yao Yao <yayao@google.com>
License: 
Requires-Python: >=3.11
License-File: LICENSE
License-File: NOTICE
Requires-Dist: mobly>=1.12.2
Dynamic: author-email
Dynamic: home-page
Dynamic: license-file
Dynamic: requires-python
